asrtoolkit/__init__.py
asrtoolkit/clean_formatting.py
asrtoolkit/convert_transcript.py
asrtoolkit/degrade_audio_file.py
asrtoolkit/extract_excel_spreadsheets.py
asrtoolkit/prepare_audio_corpora.py
asrtoolkit/split_audio_file.py
asrtoolkit/validate_stm.py
asrtoolkit/wer.py
asrtoolkit/data_handlers/__init__.py
asrtoolkit/data_handlers/data_handlers_common.py
asrtoolkit/data_handlers/greenkey.py
asrtoolkit/data_handlers/html.py
asrtoolkit/data_handlers/json.py
asrtoolkit/data_handlers/srt.py
asrtoolkit/data_handlers/stm.py
asrtoolkit/data_handlers/txt.py
asrtoolkit/data_handlers/vtt.py
asrtoolkit/data_handlers/webvtt_common.py
asrtoolkit/data_structures/__init__.py
asrtoolkit/data_structures/audio_file.py
asrtoolkit/data_structures/corpus.py
asrtoolkit/data_structures/segment.py
asrtoolkit/data_structures/time_aligned_text.py
asrtoolkit/file_utils/__init__.py
asrtoolkit/file_utils/common_file_operations.py
asrtoolkit/file_utils/name_cleaners.py
asrtoolkit-0.1.15.dist-info/METADATA
asrtoolkit-0.1.15.dist-info/RECORD
asrtoolkit-0.1.15.dist-info/WHEEL
asrtoolkit-0.1.15.dist-info/entry_points.txt
asrtoolkit-0.1.15.dist-info/top_level.txt
asrtoolkit-0.1.15.dist-info/zip-safe
