Metadata-Version: 2.1
Name: asrtoolkit
Version: 0.1.15
Summary: The GreenKey ASRToolkit provides tools for automatic speech recognition (ASR) file conversion and corpora organization.
Home-page: http://github.com/finos-voice/greenkey-asrtoolkit
Author: Matthew Goldey
Author-email: mgoldey@greenkeytech.com
License: Apache v2
Keywords: asr speech recognition greenkey word error rate
Platform: UNKNOWN
Classifier: Programming Language :: Python :: 3
Classifier: Operating System :: OS Independent
Provides-Extra: dev
Requires-Dist: beautifulsoup4
Requires-Dist: editdistance
Requires-Dist: num2words
Requires-Dist: pytest
Requires-Dist: termcolor
Requires-Dist: tqdm
Requires-Dist: webvtt-py
Requires-Dist: xlrd
Provides-Extra: dev
Requires-Dist: pandas; extra == 'dev'
